[
  {
    "id": "17761458318740",
    "timestamp": "2026-04-14T05:50:31.874Z",
    "ticker": "DIA",
    "en": {
      "title": "Monetary Authority of Singapore Tightens Policy as Middle East Conflict Escalates Inflationary Pressures",
      "content": "The Monetary Authority of Singapore (MAS) signaled a decisive shift in its policy stance on Friday, moving to tighten monetary settings in an effort to insulate the city-state from a fresh wave of global inflationary pressures. The move, which comes as military escalations between Iran and regional adversaries threaten to destabilize global energy markets, underscores the vulnerability of trade-dependent economies to geopolitical shocks. Unlike most central banks that manage interest rates, the MAS manages monetary policy through the exchange rate, allowing the Singapore dollar to appreciate against a basket of currencies to blunt the impact of imported inflation.\n\nEconomists note that the timing of this tightening reflects an urgent assessment of the risks posed by crude oil volatility. With Singapore serving as a critical node in global supply chains and a major refining hub, any sustained disruption in the Strait of Hormuz has an immediate and compounding effect on domestic price levels. The central bank announced it would slightly increase the slope of the Singapore Dollar Nominal Effective Exchange Rate (SGDNEER) policy band, a move intended to exert downward pressure on the costs of fuel and food imports. This technical adjustment essentially strengthens the local currency, making foreign goods and services cheaper for residents and businesses.\n\nThe decision highlights a growing divergence in global monetary strategy. While some Western central banks have begun to contemplate the timing of potential rate cuts as their domestic economies cool, the MAS is prioritizing the stabilization of price expectations. Core inflation in Singapore remains a primary concern for policymakers, who are wary of secondary effects where higher energy costs seep into transport, manufacturing, and consumer services. By strengthening the local currency, the MAS is effectively raising a defensive wall against the rising cost of Brent crude, which has fluctuated wildly since the onset of hostilities in the Middle East.\n\nMarket analysts suggest that this pre-emptive strike by the MAS could be a bellwether for other Asian economies. The region, which is a net importer of energy, faces a difficult balancing act between supporting post-pandemic recovery and curbing the erosion of purchasing power. The MAS statement acknowledged that while domestic demand remains resilient, the external environment has become significantly more clouded. The risk of a broader regional conflict introduces a level of uncertainty that has forced a recalibration of the inflation outlook for the remainder of the fiscal year.\n\nFor investors, the strengthening of the Singapore dollar provides a measure of stability in an otherwise volatile foreign exchange market. However, the move is not without its risks. A stronger currency could potentially dampen the competitiveness of Singapore's exports at a time when global demand for electronics and manufactured goods is already showing signs of fatigue. The MAS must navigate a narrow corridor between price stability and economic growth, ensuring that the currency appreciation does not inadvertently stifle the momentum of the domestic service sector.\n\nThe broader implications for global trade are significant. As a bellwether for the health of international commerce, Singapore’s pivot toward tightening suggests that the era of high inflation may be stickier than previously anticipated. If energy prices continue to be driven by geopolitical conflict rather than market fundamentals, central banks across the world may be forced into more aggressive stances, potentially delaying the global transition to a lower-interest-rate environment. For now, the MAS has sent a clear signal to the markets: in the face of rising geopolitical risks, price stability remains the paramount objective for the city-state's financial stewards.",
      "keywords": [
        "MAS",
        "Singapore",
        "Monetary Policy",
        "Inflation",
        "Iran",
        "Geopolitical Risk",
        "SGDNEER"
      ],
      "tags": [
        "Central Banking",
        "Energy Markets",
        "Macroeconomics",
        "Asian Markets"
      ]
    },
    "zh": {
      "title": "中东冲突加剧通胀压力 新加坡金融管理局宣布收紧货币政策",
      "content": "新加坡金融管理局（MAS）周五发出明确的政策转向信号，宣布收紧货币政策，旨在保护该国免受新一轮全球通胀压力的冲击。随着伊朗与地区对手之间的军事升级威胁到全球能源市场的稳定，此举突显了依赖贸易的经济体在面对地缘政治冲击时的脆弱性。与大多数通过利率管理政策的中央银行不同，新加坡金管局通过汇率进行货币政策调节，允许新加坡元对一篮子货币升值，以削弱输入性通胀的影响。\n\n经济学家指出，此次收紧政策的时机反映了对原油波动风险的紧急评估。新加坡作为全球供应链的关键节点和主要的炼油枢纽，霍尔木兹海峡的任何持续中断都会对国内物价水平产生即时且复合的影响。中央银行宣布将略微提高新加坡元名义有效汇率（SGDNEER）政策区间的斜率，此举旨在对燃料和食品进口成本施加下行压力。这种技术性调整实质上加强了本国货币，使居民和企业购买外国商品和服务更加便宜。\n\n这一决定凸显了全球货币策略日益增长的分歧。虽然一些西方央行随着国内经济降温已开始考虑降息的时机，但新加坡金管局仍将稳定价格预期放在首位。新加坡的核心通胀仍是政策制定者的主要关注点，他们担心高能源成本会渗透到交通、制造业和消费者服务领域，产生二次效应。通过走强本币，新加坡金管局实际上是针对布伦特原油成本上升筑起了一道防线，自中东敌对行动开始以来，油价波动剧烈。\n\n市场分析人士认为，金管局的这一预见性举措可能是其他亚洲经济体的风向标。作为能源净进口区，亚洲面临着在支持疫情后复苏与遏制购买力侵蚀之间的艰难平衡。金管局在声明中承认，尽管国内需求保持韧性，但外部环境已显著变得阴云密布。更大范围地区冲突的风险引入了不确定性，迫使政策制定者重新校准本财政年度剩余时间的通胀预期。\n\n对于投资者而言，新加坡元的走强在动荡的外汇市场中提供了一定程度的稳定性。然而，此举并非没有风险。在全球对电子产品和制成品的需求已显露疲态之际，更强劲的货币可能会削弱新加坡出口的竞争力。金管局必须在价格稳定与经济增长之间的狭窄走廊中穿行，确保货币升值不会无意中扼杀国内服务业的增长势头。\n\n对全球贸易的广泛影响不容忽视。作为国际商业健康状况的晴雨表，新加坡转向紧缩表明，高通胀时代可能比此前预期的更具粘性。如果能源价格继续由地缘政治冲突而非市场基本面驱动，全球央行可能会被迫采取更激进的立场，从而推迟全球向低利率环境的过渡。就目前而言，金管局向市场发出了一个明确信号：面对日益增长的地缘政治风险，价格稳定仍是该国金融决策者的首要目标。",
      "keywords": [
        "新加坡金管局",
        "货币政策",
        "通货膨胀",
        "伊朗",
        "地缘政治风险",
        "新加坡元汇率"
      ],
      "tags": [
        "中央银行",
        "能源市场",
        "宏观经济",
        "亚洲市场"
      ]
    }
  },
  {
    "id": "17761457168090",
    "timestamp": "2026-04-14T05:48:36.809Z",
    "ticker": "DIA",
    "en": {
      "title": "Diplomatic Overtures in Middle East Spark Global Market Rally as Oil and Dollar Retreat",
      "content": "Global financial markets experienced a notable shift in sentiment during Tuesday’s trading session as burgeoning hopes for a diplomatic resolution between the United States and Iran prompted a widespread pivot toward risk-on assets. Equity markets across the major financial hubs in New York, London, and Tokyo saw broad-based gains, while the traditional safe havens of the U.S. dollar and crude oil retreated from recent highs. This recalibration of risk reflects a growing optimism among institutional investors that a cooling of tensions in the Middle East could mitigate one of the most significant geopolitical tail risks currently facing the global economy.\n\nIn New York, benchmark indices opened higher as market participants digested reports suggesting that back-channel communications between Washington and Tehran might be yielding a framework for de-escalation. While official statements remain guarded, the mere prospect of a diplomatic breakthrough was enough to trigger a sell-off in the energy sector, which has been buoyed for months by a persistent geopolitical risk premium. Brent crude and West Texas Intermediate both saw declines of over two percent, as traders recalibrated the likelihood of supply disruptions in the Strait of Hormuz. The easing of energy prices provides a much-needed reprieve for central banks, particularly the Federal Reserve, which continues to grapple with the complexities of bringing inflation back to its two-percent target without inducing a recession.\n\nThe foreign exchange markets mirrored this sentiment. The U.S. Dollar Index, which often serves as a sanctuary for capital during periods of heightened international friction, softened as investors rotated out of the greenback and into cyclical currencies and emerging market assets. Analysts at major investment banks noted that the dollar’s retreat is a direct reflection of a 'de-risking' environment. When the probability of a direct military confrontation or severe regional escalation diminishes, the necessity of holding liquid, dollar-denominated safety assets wanes, allowing for a broader distribution of capital into global equities.\n\nHowever, seasoned market strategists urge a degree of cautious skepticism. The history of U.S.-Iran relations is defined by cycles of tentative rapprochement followed by swift reversals. For the current market rally to find sustainable footing, investors will require more than just rhetorical signals. Concrete steps toward a formal agreement or a verifiable reduction in regional hostilities will be necessary to keep the geopolitical risk premium from returning. The current market reaction is, in many ways, a relief rally, predicated on the avoidance of a worst-case scenario rather than the solidification of a long-term peace.\n\nFrom a macroeconomic perspective, the implications of a sustained US-Iran resolution are profound. Lower oil prices act as a de facto tax cut for consumers and reduce input costs for manufacturers, potentially accelerating the 'soft landing' narrative that has dominated market discussions this year. Furthermore, a reduction in Middle Eastern tensions allows the U.S. administration to focus its diplomatic and economic resources on other pressing issues, such as trade relations in the Indo-Pacific and the ongoing structural shifts in the European energy market.\n\nAs the trading day progresses, the focus remains on the flow of information from diplomatic circles. Volume in the options market suggests that while investors are participating in the rally, they are also maintaining hedges against a sudden return to volatility. In the complex theater of global finance, the line between a breakthrough and a breakdown remains thin, but for today, the markets are choosing to price in the hope of a more stable geopolitical landscape.",
      "keywords": [
        "Geopolitics",
        "Crude Oil",
        "US Dollar",
        "Equity Markets",
        "Diplomacy",
        "Federal Reserve",
        "Middle East"
      ],
      "tags": [
        "Finance",
        "Economy",
        "Global Markets",
        "Energy Sector"
      ]
    },
    "zh": {
      "title": "中东外交局势显露转机 全球股市上涨而原油与美元应声回落",
      "content": "周二交易时段，全球金融市场情绪出现显著变化。随着美国与伊朗之间达成外交解决的可能性增加，投资者开始转向风险资产。纽约、伦敦和东京等主要金融枢纽的股市普遍上涨，而作为传统避险资产的美元和原油价格则从近期高点回落。这种风险权重的重新分配反映了机构投资者日益增长的乐观情绪，即中东局势的降温可能会缓解目前全球经济面临的最重大地缘政治尾部风险之一。\n\n在纽约，基准指数开盘走高。此前有报道称，华盛顿与德黑兰之间的后台沟通可能正在为降温局势建立框架。尽管官方声明依然谨慎，但外交突破的前景足以引发能源部门的抛售。由于数月来地缘政治风险溢价的支撑，原油价格一直处于高位，但随着交易员重新评估霍尔木兹海峡供应中断的可能性，布伦特原油和西德克萨斯中质原油均下跌超过2%。能源价格的缓解为各国央行，特别是美联储，提供了宝贵的喘息机会，美联储目前仍在努力应对在不引发衰退的情况下将通胀率降回2%目标的复杂挑战。\n\n外汇市场的表现也印证了这一情绪。美元指数通常在国际冲突加剧期间充当资金避风港，但随着投资者从美元转向周期性货币和新兴市场资产，美元指数应声走软。大型投资银行的分析师指出，美元的回落是“去风险”环境的直接反映。当地缘政治对抗或地区冲突升级的概率降低时，持有高流动性、以美元计价的安全资产的必要性就会下降，从而使资本能够更广泛地分布到全球股市。\n\n然而，资深市场策略师敦促保持一定程度的谨慎怀疑。美伊关系的历史充满了尝试性接触后迅速逆转的周期。为了使当前的股市反弹具有可持续性，投资者需要的不仅仅是口头信号。要防止地缘政治风险溢价回升，就需要采取具体的步骤来达成正式协议或可核实的地区敌对行动减少。在许多方面，目前的市场反应是一种“解脱性反弹”，其前提是规避了最坏的情况，而不是确立了长期的和平。\n\n从宏观经济角度来看，美伊局势若能持续解决，其影响将是深远的。较低的油价实际上相当于为消费者减税，并降低了制造商的投入成本，这可能会加速今年主导市场讨论的“软着陆”预期。此外，中东紧张局势的缓解使美国政府能够将其外交和经济资源集中在其他紧迫问题上，例如印太地区的贸易关系以及欧洲能源市场的持续结构性转变。\n\n随着交易日的进行，市场的焦点仍集中在来自外交渠道的信息流上。期权市场的成交量表明，尽管投资者正在参与反弹，但他们也在针对波动的突然回归维持对冲。在全球金融的复杂剧场中，突破与崩溃之间的界限依然脆弱，但就目前而言，市场选择将地缘政治格局趋于稳定的希望计入定价。",
      "keywords": [
        "地缘政治",
        "原油",
        "美元",
        "股票市场",
        "外交",
        "美联储",
        "中东"
      ],
      "tags": [
        "金融",
        "经济",
        "全球市场",
        "能源行业"
      ]
    }
  },
  {
    "id": "17760880416840",
    "timestamp": "2026-04-13T13:47:21.684Z",
    "ticker": "DIA",
    "en": {
      "title": "Energy Pressures and Banking Results Weigh on Market Sentiment Amid Diplomatic Stalemate",
      "content": "Wall Street entered the new trading week grappling with a complex intersection of geopolitical instability and cooling corporate performance. Market participants are recalibrating their portfolios in response to a surge in energy prices and a notable retreat in the financial sector, specifically following a disappointing earnings release from Goldman Sachs. These developments have heightened concerns regarding the durability of the current economic expansion and the persistent nature of inflationary pressures.\n\nThe most immediate catalyst for market movement is the renewed volatility in the energy complex. Crude oil prices climbed significantly on Monday morning following reports that diplomatic discussions between the United States and Iran have reached a substantive impasse. The failure to secure a breakthrough in these negotiations diminishes the likelihood of an imminent return of Iranian supply to international markets. For global energy markets already strained by logistical constraints and production quotas, the prospect of prolonged scarcity is driving benchmarks higher. Analysts suggest that if oil prices sustain this upward trajectory, the Federal Reserve may find it increasingly difficult to engineer a soft landing, as energy costs permeate nearly every sector of the consumer price index.\n\nParallel to the energy crunch, the banking sector is facing its own set of challenges. Shares of Goldman Sachs Group Inc. declined sharply after the firm reported quarterly earnings that fell short of consensus estimates. The shortfall was largely attributed to a significant slowdown in investment banking activity and higher-than-anticipated operating expenses. As a bellwether for the broader financial industry, Goldman’s performance signals a tightening environment for capital markets. The exuberant deal-making that defined much of the post-pandemic recovery appears to be yielding to a more cautious era, characterized by rising interest rates and a more selective approach to mergers and acquisitions. Investors are now closely monitoring whether other major financial institutions will exhibit similar signs of strain as the cost of capital continues to rise.\n\nMarket commentators, including prominent analysts such as Jim Cramer, have identified several critical factors that will define the narrative for the coming week. Beyond oil and bank earnings, the focus remains on the resilience of the consumer and the stability of the technology sector. The divergence between different market segments suggests that the period of broad-based equity growth may be giving way to a more fragmented and volatile environment. Strategic positioning is becoming increasingly difficult as the traditional correlations between asset classes shift in response to macroeconomic uncertainty. \n\nLooking ahead, the focus will likely remain on the trajectory of the 10-year Treasury yield and the subsequent impact on equity valuations. If the combination of high energy prices and disappointing corporate guidance persists, it could lead to a broader reassessment of risk assets. For now, the market remains in a state of watchful waiting, sensitive to every development in international diplomacy and every granular detail in the ongoing earnings season. The ability of the market to absorb these shocks will be a defining test of institutional resilience in the face of a rapidly evolving global landscape. The upcoming days will be instrumental in determining whether this Monday's retreat is a temporary setback or the beginning of a more profound structural adjustment in investor expectations.",
      "keywords": [
        "Oil Prices",
        "Goldman Sachs",
        "Earnings Season",
        "US-Iran Relations",
        "Market Volatility",
        "Federal Reserve"
      ],
      "tags": [
        "Finance",
        "Energy",
        "Banking",
        "Geopolitics",
        "Economy"
      ]
    },
    "zh": {
      "title": "地缘外交僵局与银行财报疲软打压市场情绪",
      "content": "华尔街在本周伊始便陷入了地缘政治不稳定与企业业绩降温的复杂交织之中。受能源价格飙升以及金融板块明显回落的影响，市场参与者正忙于重新调整投资组合，尤其是高盛集团发布的财报令人失望。这些进展加剧了市场对当前经济增长韧性以及通胀压力持续性的担忧。\n\n市场波动最直接的催化剂是能源领域的波动加剧。周一早盘，原油价格大幅上涨。此前有报道称，美国与伊朗之间的外交谈判陷入了实质性僵局。谈判未能取得突破，降低了伊朗原油供应近期重返国际市场的可能性。对于已经受到物流限制和生产配额压力的全球能源市场而言，长期短缺的前景正在推高基准价格。分析人士指出，如果油价维持这一上升轨迹，美联储可能发现实现经济软着陆变得日益困难，因为能源成本已渗透到消费者物价指数的几乎每一个领域。\n\n在能源危机出现的同时，银行业也面临着自身的挑战。高盛集团股价在公布季度收益低于一致预期后大幅下跌。收益下滑主要归因于投行业务大幅放缓以及运营支出高于预期。作为整个金融行业的风向标，高盛的表现预示着资本市场环境的收紧。在疫情后复苏期间大行其道的交易热潮似乎正在让位于一个更加谨慎的时代，其特点是利率上升以及对并购采取更为挑剔的态度。随着资金成本持续上升，投资者目前正密切关注其他主要金融机构是否会出现类似的压力迹象。\n\n包括吉姆·克莱默在内的知名市场评论员指出，有几个关键因素将定义本周的市场走势。除了石油和银行收益外，焦点仍在于消费者的韧性和科技行业的稳定性。不同细分市场之间的分化表明，广泛的股票增长期可能正让位于一个更加支离破碎和波动的环境。随着传统资产类别间的相关性因宏观经济不确定性而发生变化，战略布局正变得越来越困难。\n\n展望未来，焦点可能会集中在10年期国债收益率的轨迹及其对股票估值的后续影响上。如果高能源价格与令人失望的企业指引相结合的情况持续下去，可能会导致市场对风险资产进行更广泛的重新评估。目前，市场仍处于观望状态，对国际外交的每一个发展以及正在进行的财报季中的每一个细节都非常敏感。在快速演变的全球格局面前，市场消化这些冲击的能力将是对机构韧性的一次定义性测试。未来几天的走势将决定本周一的回调是暂时性的挫折，还是投资者预期发生更深层次结构性调整的开始。",
      "keywords": [
        "原油价格",
        "高盛",
        "财报季",
        "美伊关系",
        "市场波动",
        "美联储"
      ],
      "tags": [
        "金融",
        "能源",
        "银行业",
        "地缘政治",
        "经济"
      ]
    }
  },
  {
    "id": "17760651381980",
    "timestamp": "2026-04-13T07:25:38.198Z",
    "ticker": "DIA",
    "en": {
      "title": "Gold Prices Recede as Stalled U.S.-Iran Diplomacy and Persistent Inflationary Pressures Weigh on Sentiment",
      "content": "The global bullion market experienced a notable retrenchment during Wednesday’s trading session as a confluence of geopolitical friction and macroeconomic headwinds dampened investor appetite for the precious metal. Gold prices retreated from recent highs, a move primarily attributed to the collapse of diplomatic negotiations between the United States and Iran, alongside a growing consensus that inflationary pressures in the domestic economy will remain elevated for a more protracted period than previously anticipated.\n\nMarket participants had closely monitored the latest round of talks aimed at reviving the Joint Comprehensive Plan of Action. However, the failure to secure a breakthrough has introduced a fresh layer of complexity to the Middle Eastern geopolitical landscape. While gold is traditionally viewed as a primary safe-haven asset during times of international instability, the immediate market reaction was characterized by a sell-off rather than a flight to safety. Analysts suggest this counterintuitive move stems from the market’s pivot toward the implications of stalled diplomacy on global energy supplies and, by extension, its contribution to structural inflation.\n\nThe inability to reach a diplomatic resolution suggests that sanctions on Iranian oil exports will remain in place for the foreseeable future, tightening global supply and maintaining upward pressure on crude prices. For the Federal Reserve, this persistent energy-led inflation complicates the path toward monetary easing. As the prospect of a rate cut remains elusive, the opportunity cost of holding non-yielding assets like gold has risen. The psychological threshold for investors has shifted as they recalibrate their portfolios to account for a higher-for-longer interest rate environment.\n\nInstitutional sell-off signals were reinforced by a strengthening U.S. dollar, which gained momentum against a basket of major currencies. A robust greenback typically exerts downward pressure on dollar-denominated commodities, making gold more expensive for holders of foreign currencies. This currency dynamic, coupled with rising yields on the 10-year Treasury note, has created a challenging environment for gold to sustain its upward trajectory. Fixed-income instruments are currently offering competitive real returns, further detracting from the allure of precious metals.\n\nFurthermore, recent consumer price index data continues to haunt the markets. Despite aggressive tightening cycles by central banks, core inflation figures remain stubbornly above target. This has led to a fundamental reassessment of the gold-inflation relationship. While gold is often touted as an inflation hedge, its performance in the current cycle has been erratic, frequently overshadowed by the Federal Reserve’s aggressive posture. The central bank's commitment to price stability suggests that liquidity will remain restricted, a factor that historically precedes a cooling in commodity speculation.\n\nFrom a technical perspective, the breach of key support levels has triggered automated sell orders, accelerating the intraday decline. Traders are now looking toward the upcoming release of the Federal Open Market Committee minutes for further clarity on the central bank’s internal deliberations. Should the minutes reveal a hawkish consensus regarding the persistence of price pressures, gold could face additional downward volatility. Conversely, any indication of a softening in the labor market might provide the necessary catalyst for a stabilization in prices.\n\nIn conclusion, the intersection of failed Middle Eastern diplomacy and a rigid inflationary backdrop has left gold in a precarious position. The market is currently prioritizing yield and dollar strength over traditional safe-haven narratives. As long as the geopolitical stalemate continues to feed into the global inflationary cycle, the path of least resistance for gold prices appears to be toward the downside. Investors are advised to maintain a cautious stance as the global financial architecture remains sensitive to both diplomatic volatility and the Federal Reserve’s next move.",
      "keywords": [
        "Gold Prices",
        "Inflation",
        "US-Iran Relations",
        "Federal Reserve",
        "Monetary Policy",
        "Commodities"
      ],
      "tags": [
        "Finance",
        "Geopolitics",
        "Market Analysis",
        "Central Banking"
      ]
    },
    "zh": {
      "title": "美伊外交陷入僵局与持续通胀压力导致金价回落",
      "content": "全球黄金市场在周三的交易时段出现了显著的回撤，地缘政治摩擦与宏观经济逆风的交织抑制了投资者对这种贵金属的胃口。金价从近期高点回落，这一波动主要归因于美伊外交谈判的破裂，以及市场日益达成共识，即国内经济的通胀压力持续时间将比此前预期的更为持久。\n\n市场参与者一直密切关注旨在恢复《联合全面行动计划》的最新一轮谈判。然而，未能取得突破为中东地缘政治格局增添了新的复杂性。虽然黄金传统上被视为国际动荡时期的首要避险资产，但市场的即时反应却是抛售而非涌向避险资产。分析人士认为，这种反直觉的走势源于市场转向关注外交僵局对全球能源供应的影响，进而关注其对结构性通胀的推升作用。\n\n外交解决方案的缺失意味着对伊朗石油出口的制裁在可预见的未来仍将维持，这将收紧全球供应并对原油价格保持上行压力。对于美联储而言，这种由能源驱动的持续通胀使得货币宽松之路变得更加复杂。由于降息前景依然渺茫，持有黄金等无息资产的机会成本已经上升。随着投资者重新调整其投资组合以应对长期高利率环境，投资者的心理门槛已经发生了变化。\n\n机构抛售信号因美元走强而得到加强，美元兑一篮子主要货币势头强劲。坚挺的本币通常会对以美元计价的商品施加下行压力，使外币持有者购买黄金的成本更高。这种汇率动态，加上10年期国债收益率的上升，为黄金维持上行轨迹创造了挑战。固定收益工具目前提供具有竞争力的实际回报，进一步削弱了贵金属的吸引力。\n\n此外，近期的消费者价格指数（CPI）数据继续困扰着市场。尽管各国央行实施了激进的紧缩周期，但核心通胀数据仍顽固地高于目标。这导致了对黄金与通胀关系的根本性重新评估。虽然黄金常被吹捧为对冲通胀的工具，但它在本轮周期中的表现一直不稳定，经常被美联储的激进姿态所掩盖。央行对价格稳定的承诺表明流动性将继续受限，这一因素在历史上往往先于大宗商品投机的降温。\n\n从技术角度看，关键支撑位的突破触发了自动卖单，加速了盘中下跌。交易员目前正期待即将公布的联邦公开市场委员会（FOMC）会议纪要，以进一步了解央行内部的审议情况。如果纪要显示出关于价格压力持续性的鹰派共识，金价可能会面临额外的下行波动。相反，劳动力市场疲软的任何迹象都可能为价格稳定提供必要的催化剂。\n\n总之，中东外交失败与僵硬的通胀背景交织，使黄金处于危险境地。目前市场优先考虑收益率和美元走强，而非传统的避险叙事。只要地缘政治僵局继续推升全球通胀循环，金价阻力最小的路径似乎就是下行。建议投资者保持谨慎态度，因为全球金融架构对外交波动和美联储的下一步行动依然高度敏感。",
      "keywords": [
        "金价",
        "通胀",
        "美伊关系",
        "美联储",
        "货币政策",
        "大宗商品"
      ],
      "tags": [
        "金融",
        "地缘政治",
        "市场分析",
        "央行"
      ]
    }
  },
  {
    "id": "17760535310620",
    "timestamp": "2026-04-13T04:12:11.062Z",
    "ticker": "DIA",
    "en": {
      "title": "U.S. Signals Naval Blockade of Iran Following Collapse of Diplomatic Talks",
      "content": "The geopolitical landscape of the Middle East underwent a seismic shift on Tuesday as the United States announced its intention to implement a naval blockade against Iran. The decision comes in the immediate wake of failed diplomatic negotiations in Geneva, where representatives from Washington and Tehran were unable to reach an agreement regarding regional security and nuclear enrichment protocols. This escalation from economic sanctions to direct maritime interdiction marks a turning point in Western foreign policy and carries profound implications for global financial markets, energy security, and the precarious balance of international trade.\n\nEnergy markets reacted with predictable volatility. Brent crude futures surged by more than four percent in after-hours trading, while West Texas Intermediate followed a similar trajectory. Commodity analysts suggest that the blockade essentially removes approximately 1.5 million barrels of Iranian oil from the daily global supply, a deficit that will be difficult for other producers to fill on short notice. While OPEC+ has maintained significant spare capacity, the technical and political hurdles to an immediate production hike are substantial. Investors are now pricing in a sustained geopolitical risk premium, with some Wall Street desks raising their year-end price targets for oil to well above one hundred dollars per barrel.\n\nThe most acute concern for global shipping and insurance sectors is the potential for retaliation in the Strait of Hormuz. This narrow waterway serves as the transit point for nearly twenty percent of the world’s daily oil consumption. A naval blockade by the United States increases the probability that Tehran may attempt to disrupt traffic through the strait, a move that would effectively paralyse energy flows to Asia and Europe. Marine insurance premiums for tankers operating in the Persian Gulf have already begun to climb, and major shipping conglomerates are reportedly considering rerouting vessels around the Cape of Good Hope, a logistical shift that would add significant time and cost to global supply chains.\n\nFrom a macroeconomic perspective, the timing of this blockade presents a formidable challenge for central banks. Both the Federal Reserve and the European Central Bank have been navigating a delicate path toward disinflation. A sustained spike in energy prices threatens to reignite inflationary pressures, potentially forcing policymakers to maintain higher interest rates for a longer period than markets had previously anticipated. This hawkish outlook has already triggered a sell-off in sovereign debt, with the yield on the 10-year Treasury note ticking upward as investors digest the prospect of an enduring energy shock.\n\nEquity markets have displayed a bifurcated response. While the broader indices have retreated amid heightened uncertainty, defense contractors and large-cap energy firms have outperformed. The move toward a blockade suggests a protracted period of regional instability, driving capital toward traditional safe-haven assets. Gold prices have notched significant gains, reflecting a broader flight from risk as the possibility of a direct kinetic confrontation looms over the Persian Gulf.\n\nInternational reaction has been swift and divided. Traditional allies of the United States have expressed cautious support for the enforcement of international norms, yet there is palpable anxiety regarding the economic fallout. Conversely, major importers of Iranian crude, particularly in Asia, face an immediate supply crisis. The diplomatic failure in Geneva has not only closed the door on a peaceful resolution but has opened a new chapter of high-stakes brinkmanship. As the United States Navy prepares to enforce the blockade, the global financial community is left to navigate a landscape where the boundary between economic statecraft and military action has become perilously thin.",
      "keywords": [
        "Iran Blockade",
        "Oil Markets",
        "Geopolitical Risk",
        "Strait of Hormuz",
        "Energy Inflation"
      ],
      "tags": [
        "Commodities",
        "Global Economy",
        "U.S. Foreign Policy",
        "Maritime Trade"
      ]
    },
    "zh": {
      "title": "外交谈判破裂后美国宣布对伊朗实施海上封锁",
      "content": "周二，随着美国宣布计划对伊朗实施海上封锁，中东的地缘政治格局发生了剧烈震动。此前，华盛顿和德黑兰的代表在日内瓦举行的外交谈判宣告失败，双方未能就地区安全和核浓缩协议达成一致。这一从经济制裁向直接海上干预的转变，标志着西方外交政策的重大转折，并对全球金融市场、能源安全及国际贸易的脆弱平衡产生了深远影响。\n\n能源市场对此做出了预料之中的波动反应。布伦特原油期货在盘后交易中飙升超过4%，而西德克萨斯中质原油也紧随其后。大宗商品分析师指出，封锁实际上从全球每日供应中剔除了约150万桶伊朗石油，这一缺口其他生产国很难在短期内填补。尽管欧佩克+（OPEC+）保持着可观的剩余产能，但立即增产的技术和政治障碍仍然巨大。投资者目前正在将持续的地缘政治风险溢价计入价格，华盛顿一些投行已将年底油价目标上调至每桶100美元以上。\n\n全球航运和保险业最担心的核心问题是霍尔木兹海峡可能遭到的报复。这条狭窄的水道承载着全球近20%的每日石油消费量。美国的军事封锁增加了德黑兰尝试干扰该海峡交通的可能性，此举将有效瘫痪流向亚洲和欧洲的能源流动。在波斯湾运营的油轮海上保险溢价已经开始攀升，据报道，主要的航运巨头正考虑将船只改道好望角，这一物流转变将显著增加全球供应链的时间和成本。\n\n从宏观经济角度看，此次封锁的时机给各国央行带来了巨大挑战。美联储和欧洲央行一直走在通胀放缓的微妙路径上。能源价格的持续飙升威胁要重新燃起通胀压力，可能迫使政策制定者维持比市场预期更长时间的高利率。这种鹰派前景已经引发了主权债务的抛售，随着投资者消化持续能源冲击的可能性，10年期国债收益率有所上升。\n\n股票市场呈现出分化反应。虽然大盘指数在不确定性增加的情况下回落，但国防承包商和大盘能源公司表现优异。转向封锁意味着该地区将进入长期的不稳定期，驱动资本流向传统的避险资产。金价录得显著涨幅，反映出在波斯湾可能发生直接军事对抗的阴影下，市场普遍在规避风险。\n\n国际社会的反应迅速且分歧明显。美国的传统盟友对执行国际准则表达了谨慎支持，但对经济后果表现出明显焦虑。相反，伊朗原油的主要进口国，特别是亚洲国家，面临着迫在眉睫的供应危机。日内瓦的外交失败不仅关闭了和平解决的大门，还开启了高风险博弈的新篇章。随着美国海军准备执行封锁，全球金融界不得不面对一个经济手段与军事行动之间界限变得极其模糊的新局面。",
      "keywords": [
        "伊朗封锁",
        "石油市场",
        "地缘政治风险",
        "霍尔木兹海峡",
        "能源通胀"
      ],
      "tags": [
        "大宗商品",
        "全球经济",
        "美国外交政策",
        "海运贸易"
      ]
    }
  },
  {
    "id": "17760201151400",
    "timestamp": "2026-04-12T18:55:15.140Z",
    "ticker": "DIA",
    "en": {
      "title": "Strait of Hormuz Tensions Escalate as Iran Signals New Red Lines for Naval Activity",
      "content": "The Islamic Revolutionary Guard Corps issued a definitive warning today, stating that any military vessels approaching the Strait of Hormuz will be interpreted as a direct breach of ceasefire protocols. This development marks a significant escalation in regional rhetoric, introducing a fresh layer of geopolitical risk to global energy markets already navigating a complex landscape of structural supply concerns. For institutional investors and commodity analysts, the announcement represents more than a local military maneuver; it is a calculated challenge to the stability of the worlds most vital maritime artery for crude oil.\n\nThe Strait of Hormuz, a narrow waterway through which approximately 20 percent of the worlds total petroleum consumption passes daily, remains the ultimate pressure point for global energy security. Any disruption, or even the credible threat of one, exerts immediate upward pressure on Brent Crude and West Texas Intermediate futures. Market participants are now forced to factor in a higher geopolitical risk premium, as the Iranian statement effectively narrows the margin for error in international naval operations. While physical blockades remain a worst-case scenario, the psychological impact on the shipping industry and energy derivatives is immediate.\n\nInsurance underwriters at Lloyd s of London and other major maritime insurers are expected to reassess war risk premiums for tankers traversing the Persian Gulf. In previous periods of heightened tension, these costs have surged, adding substantial overhead to the delivered price of oil. This increases the costs for global energy flows and has broader inflationary implications for the global economy, potentially complicating the efforts of central banks to manage interest rate pivots. If the transit of oil becomes significantly more expensive or hazardous, the ripple effects will be felt across global manufacturing and logistics sectors throughout the fiscal year.\n\nFrom a strategic perspective, the timing of the declaration is noteworthy. It comes at a moment when global inventories are relatively tight and the OPEC+ alliance continues to manage supply to maintain price floors. By linking naval movements to ceasefire breaches, Tehran is asserting a form of maritime sovereignty that challenges long-standing principles of freedom of navigation. This creates a diplomatic and military dilemma for the United States and its allies, who maintain a constant presence in the region to safeguard commercial lanes. The potential for a miscalculation on the water has risen significantly.\n\nEquity markets in the Middle East, particularly those in Riyadh and Dubai, showed signs of cautious trading following the news. Financial analysts suggest that the heightened rhetoric may trigger a flight to safety, benefiting safe-haven assets like gold and the U.S. dollar, while putting pressure on regional emerging market currencies. For commodity traders, the focus now shifts to the official response from Washington and the European Union. A measured response could calm nerves, but any perceived provocation could lead to a feedback loop of escalation that might necessitate a rerouting of cargo around the Cape of Good Hope, significantly increasing transit times.\n\nUltimately, the threat of classifying naval proximity as a ceasefire violation introduces a volatile variable into the 2024 economic outlook. As global demand for energy remains resilient despite a slowdown in certain manufacturing hubs, the fragility of the supply chain is once again under the spotlight. Investors are advised to monitor the volatility index and energy-related derivatives closely, as the Strait of Hormuz remains the preeminent geopolitical flashpoint that could derail broader market stabilization in the coming months.",
      "keywords": [
        "Strait of Hormuz",
        "IRGC",
        "Energy Markets",
        "Oil Prices",
        "Geopolitical Risk",
        "Maritime Insurance"
      ],
      "tags": [
        "Finance",
        "Global Economy",
        "Middle East",
        "Commodities",
        "Energy Security"
      ]
    },
    "zh": {
      "title": "霍尔木兹海峡局势升级 伊朗划定海军活动新红线引发市场动荡",
      "content": "伊朗伊斯兰革命卫队今日发出严正警告，称任何靠近霍尔木兹海峡的军用舰艇都将被视为直接违反停火协议。这一进展标志着地区修辞的重大升级，为本已在结构性供应担忧中挣扎的全球能源市场引入了新的地缘政治风险。对于机构投资者和商品分析师而言，这一声明不仅是地方性的军事动作，更是对全球原油最重要海上动脉稳定性的蓄意挑战。\n\n霍尔木兹海峡作为每日承载全球约20%石油消费量的狭窄水道，始终是全球能源安全的核心压力点。任何干扰或哪怕是可信的干扰威胁，都会立即对布伦特原油和西德克萨斯中质原油期货产生上行压力。市场参与者现在被迫计入更高的地缘政治风险溢价，因为伊朗的声明实际上缩小了国际海军行动的容错空间。虽然物理封锁仍被视为极端情况，但其对航运业和能源衍生品的心理影响是即时的。\n\n伦敦劳合社及其他主要海事保险公司的承保人预计将重新评估穿行波斯湾油轮的战争风险保费。在以往紧张局势加剧期间，这些成本曾大幅飙升，为石油到岸价格增加了大量经常性开支。这种能源流动的成本增加具有更广泛的通胀影响，可能使各国央行管理利率转向的努力变得更加复杂。如果石油运输变得更加昂贵或危险，其连锁反应将在整个财政年度内波及全球制造业和物流业。\n\n从战略角度看，此次表态的时机值得关注。当前全球库存相对紧张，且OPEC+联盟继续通过管理供应来维持价格底线。通过将海军演习与违反停火协议挂钩，德黑兰正在主张一种挑战长期航行自由原则的海上主权。这为美国及其盟友制造了外交和军事困境，后者一直在该地区维持存在以维护商业航道。海上发生误判的可能性已显著上升。\n\n中东股市，特别是利雅得和迪拜的股市，在消息传出后显示出谨慎交易的迹象。金融分析师建议，言论的升级可能会触发避险情绪，有利于黄金和美元等避险资产，同时对地区新兴市场货币施加压力。对于商品交易员而言，焦点现已转向华盛顿和欧盟的官方回应。适度的反应可能会平复情绪，但任何被视为挑衅的行为都可能导致升级反馈循环，甚至可能迫使货物绕道好望角，大幅增加运输时间。\n\n最终，将海军接近行为定性为违反停火协议的威胁，为2024年的经济前景引入了一个波动的变量。尽管某些制造中心出现增长放缓，但全球能源需求依然强劲，供应链的脆弱性再次成为焦点。建议投资者密切监测波动率指数和能源相关衍生品，因为霍尔木兹海峡仍是未来几个月可能瓦解市场稳定大局的首要地缘政治爆发点。",
      "keywords": [
        "霍尔木兹海峡",
        "伊朗革命卫队",
        "能源市场",
        "油价",
        "地缘政治风险",
        "航运保险"
      ],
      "tags": [
        "金融",
        "全球经济",
        "中东局势",
        "大宗商品",
        "能源安全"
      ]
    }
  },
  {
    "id": "17760187053630",
    "timestamp": "2026-04-12T18:31:45.363Z",
    "ticker": "DIA",
    "en": {
      "title": "Reliance Industries Seeks Regulatory Pathway for Iranian Oil Imports Amid Shifting Energy Alliances",
      "content": "MUMBAI — Reliance Industries Ltd., the operator of the world’s largest refining complex, has formally petitioned the Indian government for authorization to resume imports of Iranian crude oil. This strategic maneuver comes as New Delhi navigates a tightening labyrinth of international sanctions and shifting energy alliances that have defined the global oil trade over the last several years. The move by the conglomerate, led by billionaire Mukesh Ambani, signals a potential pivot in India’s energy procurement strategy, which has recently been dominated by heavily discounted Russian barrels.\n\nAccording to sources familiar with the matter, the application for government clearance is a necessary precursor to engaging with Tehran, as Indian refiners seek to diversify their feedstock following a period of intense reliance on Russian Urals. The timing of this request is particularly significant. Indian refiners had significantly increased their intake of Russian crude after the previous administration in Washington granted specific waivers to facilitate market stability. However, with those waivers set to expire this month, the financial architecture supporting these trades faces renewed scrutiny and potential disruption.\n\nFor Reliance, the return to Iranian crude is not merely a matter of geopolitical posturing but one of operational efficiency. The company’s sophisticated Jamnagar refining complex is specifically engineered to process the heavy, sour grades that Iran typically exports. During previous periods of engagement, Iranian crude provided Reliance with favorable gross refining margins due to the proximity of the source and the specific chemical composition of the oil, which yields a high percentage of middle distillates like diesel and jet fuel. Analysts suggest that if the Indian government provides the green light, it could open a corridor for other domestic refiners to follow suit, potentially recalibrating the balance of power within the OPEC+ alliance.\n\nThe broader market implications of such a move are profound. Since the implementation of restrictive measures on Russian energy exports, India has emerged as a critical swing consumer, absorbing barrels that were previously destined for European markets. However, the impending expiration of current waivers introduces a layer of volatility that the Indian Ministry of External Affairs and the Ministry of Petroleum and Natural Gas are keen to mitigate. By seeking a path back to Iranian supply, Reliance is effectively hedging against the risk of secondary sanctions that could tighten the flow of Russian oil or increase the costs of shipping and insurance.\n\nFrom a financial perspective, the resumption of trade with Iran would likely require a sophisticated clearing mechanism to bypass the dollar-dominated global financial system, which remains largely closed to Iranian entities. Previous iterations of Indo-Iranian trade utilized a rupee-denominated escrow account at state-run banks, a model that could be revitalized to facilitate these transactions. Such a development would be closely watched by the U.S. Treasury Department, which has maintained a rigorous sanctions regime against Tehran’s energy sector.\n\nAs the global energy landscape remains in a state of flux, the decision by Reliance to seek government approval underscores the pragmatic approach taken by major Asian importers. For investors, the focus will remain on how this shift impacts the company’s quarterly earnings and the wider stability of energy prices in the Indo-Pacific region. Should the government grant the requested approvals, it would represent a significant test of India’s strategic autonomy and its ability to balance its domestic energy security requirements against the pressure of international diplomatic frameworks. The outcome of this petition will likely serve as a bellwether for the next phase of global crude distribution.",
      "keywords": [
        "Reliance Industries",
        "Iranian Crude",
        "Energy Markets",
        "Oil Sanctions",
        "India Trade"
      ],
      "tags": [
        "Energy",
        "Finance",
        "Geopolitics",
        "Oil",
        "Reliance"
      ]
    },
    "zh": {
      "title": "信实工业在能源联盟转型之际寻求进口伊朗原油的监管许可",
      "content": "孟买 —— 经营着全球最大炼油综合体的信实工业有限公司（Reliance Industries Ltd.）已正式向印度政府提出申请，请求授权恢复进口伊朗原油。这一战略举措正值新德里方面在国际制裁和不断变化的能源联盟中寻求平衡之际。由亿万富翁穆克什·安巴尼领导的这家财团的举动，标志着印度能源采购战略可能发生转向。近期，印度的能源采购一直以大幅打折的俄罗斯原油为主。\n\n据知情人士透露，申请政府许可与德黑兰方面开展接触的必要前提，因为印度炼油商在经历了高度依赖俄罗斯乌拉尔原油的时期后，正寻求实现原料来源的多样化。此次请求的时机尤为关键。在华盛顿上届政府为促进市场稳定而授予特定豁免权后，印度炼油商大幅增加了对俄罗斯原油的摄入量。然而，随着这些豁免将于本月到期，支持这些贸易的金融架构面临着新的审查和潜在的中断风险。\n\n对于信实工业而言，回归伊朗原油不仅是地缘政治姿态的问题，更是运营效率的问题。该公司位于贾姆纳格尔的先进炼油厂专门设计用于处理伊朗通常出口的重质高硫原油。在之前的合作期间，伊朗原油为信实工业提供了良好的毛炼油利润，这得益于货源的近距离以及原油的特定化学成分，这种成分能产出高比例的柴油和航空煤油等中间馏分油。分析人士认为，如果印度政府亮起绿灯，这可能会为其他国内炼油商效仿开辟通道，并可能重新调整欧佩克+（OPEC+）联盟内部的权力平衡。\n\n此举对更广泛市场的潜在影响是深远的。自针对俄罗斯能源出口的限制措施实施以来，印度已成为一个关键的摇摆消费国，吸收了此前流向欧洲市场的原油。然而，当前豁免权的即将到期引入了一层波动性，印度外交部和石油与天然气部正致力于缓解这种波动。通过寻求重返伊朗供应的路径，信实工业实际上是在对冲针对俄罗斯石油流动的次级制裁风险，或是航运和保险成本增加的风险。\n\n从金融角度看，恢复与伊朗的贸易可能需要一种复杂的清算机制，以绕过以美元为主导的全球金融系统，因为该系统在很大程度上仍对伊朗实体关闭。此前印度与伊朗的贸易曾利用在国有银行开设的卢比计价托管账户，这种模式可能会被重启以促进这些交易。此类进展将受到美国财政部的严密监视，后者一直对伊朗能源部门保持着严格的制裁机制。\n\n在全球能源格局仍处于变动之中的背景下，信实工业寻求政府批准的决定凸显了亚洲主要进口国所采取的务实态度。对于投资者而言，关注点将集中在这一转变如何影响公司的季度盈利以及印太地区能源价格的整体稳定性。如果政府批准了相关请求，这将是对印度战略自主权及其在平衡国内能源安全需求与国际外交框架压力之间能力的一次重大考验。这一请愿的结果可能会成为全球原油分配下一阶段的晴雨表。",
      "keywords": [
        "信实工业",
        "伊朗原油",
        "能源市场",
        "石油制裁",
        "印度贸易"
      ],
      "tags": [
        "能源",
        "金融",
        "地缘政治",
        "石油",
        "信实"
      ]
    }
  },
  {
    "id": "17760152874750",
    "timestamp": "2026-04-12T17:34:47.475Z",
    "ticker": "DIA",
    "en": {
      "title": "Escalating Tensions in the Strait of Hormuz Threaten Global Energy Security and Market Stability",
      "content": "TEHRAN — The Islamic Revolutionary Guard Corps issued a definitive proclamation on Thursday, stating that any approach by foreign military vessels toward the Strait of Hormuz will be interpreted as a direct breach of the current ceasefire. This development has immediately recalibrated risk assessments across global energy markets, as the strait remains the world’s most significant maritime chokepoint for petroleum transit. For institutional investors and commodity traders, the rhetoric signals a potential end to the relative stability that has governed the region's shipping lanes in recent months.\n\nThe Strait of Hormuz, a narrow waterway between Oman and Iran, facilitates the passage of approximately 21 million barrels of oil per day, representing roughly one-fifth of global liquid petroleum consumption. Any disruption to this artery would likely catalyze a liquidity crunch in the physical oil market, sending ripples through the global economy. Analysts at major financial institutions are already revising their short-term price targets for Brent Crude, noting that the geopolitical risk premium is once again a primary driver of market volatility. The market is sensitive not just to the threat of blockade, but to the increased costs associated with navigating an increasingly hostile environment.\n\nMarket participants are particularly concerned about the implications for maritime insurance and freight costs. Following the announcement by the Revolutionary Guard, war risk insurance premiums for tankers traversing the Persian Gulf are expected to see a marked increase. This spike in operational costs will inevitably be passed down the supply chain, adding to the inflationary pressures that central banks are currently struggling to contain. The prospect of a prolonged naval standoff could lead to a strategic shift in shipping routes, although few viable alternatives exist that can match the capacity of the Hormuz passage, making the global economy uniquely vulnerable to Iranian maritime policy.\n\nFrom a macroeconomic perspective, the timing of this escalation is precarious. As the Federal Reserve and the European Central Bank navigate a delicate transition toward lower interest rates, a sudden energy price shock could stall disinflationary trends. This would force a reassessment of monetary policy trajectories, potentially keeping interest rates higher for longer to combat the secondary effects of rising fuel costs. Furthermore, the tension impacts the broader Middle Eastern investment landscape, where sovereign wealth funds and private equity firms have been seeking to diversify regional economies away from fossil fuel reliance. Increased volatility often deters the foreign direct investment necessary for such transitions.\n\nGeopolitical analysts suggest that the Guard Corps' stance is a calculated move designed to assert regional hegemony and test the resolve of international maritime coalitions. However, the financial implications are far from theoretical. We are seeing a rotation into defensive assets, with gold and high-grade government bonds attracting safe-haven flows. Conversely, shipping stocks and energy-intensive manufacturing sectors are facing increased scrutiny as analysts weigh the costs of potential supply chain ruptures. The energy sector, while benefiting from higher spot prices, faces the long-term risk of demand destruction if prices remain elevated.\n\nIn the coming days, the focus will remain on the naval movements within the Gulf of Oman and the Persian Gulf. If the threats manifest into kinetic action or ship seizures, the initial market reaction—currently characterized as a cautious repricing of risk—could transform into a full-scale commodities rally. For now, the global financial community remains on high alert, monitoring satellite data and diplomatic channels for any signs of de-escalation or further provocation in this critical corridor of international trade. The fragility of global supply chains has once again been laid bare by the strategic posturing of a single regional power.",
      "keywords": [
        "Strait of Hormuz",
        "IRGC",
        "Energy Markets",
        "Oil Prices",
        "Geopolitical Risk",
        "Shipping Insurance"
      ],
      "tags": [
        "Finance",
        "Energy",
        "Geopolitics",
        "Commodities",
        "Middle East"
      ]
    },
    "zh": {
      "title": "霍尔木兹海峡紧张局势升级 威胁全球能源安全与市场稳定",
      "content": "德黑兰——伊朗伊斯兰革命卫队周四发布明确公告，称外国军舰任何靠近霍尔木兹海峡的行为都将被视为直接违反现行停火协议。由于该海峡仍是全球最重要的石油运输海上咽喉，这一进展立即重新调整了全球能源市场的风险评估。对于机构投资者和商品交易商而言，这一措辞标志着近几个月来管理该地区航道相对稳定的状态可能宣告结束。\n\n霍尔木兹海峡是位于阿曼和伊朗之间的狭窄水道，每天约有2100万桶石油通过，约占全球液体石油消费量的五分之一。这一动脉的任何中断都可能催化实物石油市场的流动性紧缩，进而波及全球经济。主要金融机构的分析师已经在修订布伦特原油的短期价格目标，并指出地缘政治风险溢价再次成为市场波动的主要驱动力。市场不仅对封锁威胁感到敏感，也对在日益敌对的环境中航行所增加的成本感到担忧。\n\n市场参与者特别担心对海运保险和运费的影响。在革命卫队发布公告后，预计穿越波斯湾的油轮的战争险保费将显著上升。运营成本的这种飙升将不可避免地传递到供应链下游，加剧各国中央银行目前正努力遏制的通胀压力。长期海上对峙的前景可能导致航运路线的战略转移，尽管目前几乎没有可以与霍尔木兹海峡运力相媲美的可行替代方案，这使得全球经济在伊朗的海事政策面前显得尤为脆弱。\n\n从宏观经济角度来看，这次升级的时机非常微妙。随着美联储和欧洲央行正处于向低利率过渡的微妙时期，突然的能源价格冲击可能会阻碍通胀放缓趋势。这将迫使货币政策轨迹重新评估，为了应对燃料成本上升带来的次生影响，利率可能会在更长时间内保持在高位。此外，紧张局势还影响到更广泛的中东投资格局，那里的主权财富基金和私募股权公司一直寻求实现区域经济脱离对化石燃料依赖的多元化。波动性的增加往往会阻碍此类转型所需的外国直接投资。\n\n地缘政治分析人士认为，革命卫队的立场是旨在维护地区霸权并测试国际海上联盟决心的蓄意举动。然而，其财务影响绝非理论上的。我们正看到资金流向防御性资产，黄金和高等级政府债券吸引了避险资金。相反，随着分析师权衡潜在供应链破裂的成本，航运股和能源密集型制造业正面临更严格的审查。能源行业虽然从较高的现货价格中受益，但如果价格持续高企，则面临需求破坏的长期风险。\n\n在接下来的几天里，焦点将集中在阿曼湾和波斯湾内的海军动向。如果威胁演变为实际的军事行动或船只扣押，目前表现为风险谨慎重新定价的市场反应，可能会演变成全面的大宗商品反弹。目前，全球金融界保持高度警惕，通过卫星数据和外交渠道监测这一关键国际贸易走廊的任何缓和或进一步挑衅的迹象。全球供应链的脆弱性再次因为一个地区大国的战略姿态而暴露无遗。",
      "keywords": [
        "霍尔木兹海峡",
        "伊朗革命卫队",
        "能源市场",
        "石油价格",
        "地缘政治风险",
        "航运保险"
      ],
      "tags": [
        "金融",
        "能源",
        "地缘政治",
        "大宗商品",
        "中东"
      ]
    }
  }
]